{
  "format": "rewritten_category_object_parameters.v1",
  "category": "Pen",
  "object": {
    "id": "b2498de78580c5daadce4978a51b7c68",
    "type": "mesh",
    "source_object_index": 34,
    "concepts": [
      {
        "template": "CylindricalPenBarrel",
        "semantic": "barrel",
        "parameters": {
          "top_outer_radius": 0.07,
          "bottom_outer_radius": 0.06,
          "height": 1.07,
          "wall_thickness": 0.01,
          "position": [
            0.0,
            0.438,
            -0.01
          ],
          "rotation": [
            -0.0,
            -0.0,
            -0.0
          ]
        },
        "source": {
          "legacy_template": "Cylindrical_Barrel",
          "source_concept_index": 0
        }
      },
      {
        "template": "SinglePenCap",
        "semantic": "cap",
        "parameters": {
          "top_outer_radius": 0.07,
          "bottom_outer_radius": 0.07,
          "total_height": 0.7,
          "top_inner_radius": 0.05,
          "bottom_inner_radius": 0.05,
          "hollow_height": 0.67,
          "position": [
            0.0,
            -0.447,
            -0.01
          ],
          "rotation": [
            -0.0,
            -0.0,
            -0.0
          ]
        },
        "source": {
          "legacy_template": "Single_Cap",
          "source_concept_index": 1
        }
      },
      {
        "template": "TrifoldPenClip",
        "semantic": "clip",
        "parameters": {
          "root_size": [
            0.04,
            0.02,
            0.01
          ],
          "middle_size": [
            0.05,
            0.73,
            0.03
          ],
          "tip_size": [
            0.01,
            0.01,
            0.01
          ],
          "root_to_middle_drop": 0,
          "tip_return_drop": 0,
          "position": [
            0.0,
            -0.7969999999999999,
            0.060000000000000005
          ],
          "rotation": [
            -0.0,
            0.0,
            180.0
          ]
        },
        "source": {
          "legacy_template": "Trifold_Clip",
          "source_concept_index": 2
        }
      },
      {
        "template": "CylindricalPenButton",
        "semantic": "button",
        "parameters": {
          "top_radius": 0.06,
          "bottom_radius": 0.06,
          "height": 0.03,
          "position": [
            0.0,
            0.9730000000000001,
            -0.01
          ],
          "rotation": [
            -0.0,
            -0.0,
            -0.0
          ]
        },
        "source": {
          "legacy_template": "Cylindrical_Button",
          "source_concept_index": 3
        }
      }
    ]
  }
}