{
  "format": "rewritten_category_object_parameters.v1",
  "category": "Faucet",
  "object": {
    "id": "270123ec327ec824c36fb70296e45483",
    "type": "mesh",
    "source_object_index": 125,
    "concepts": [
      {
        "template": "Cylindrical_Base",
        "semantic": "base",
        "parameters": {
          "cylinder_count": 2,
          "primary_size": [
            0.0685,
            0.45
          ],
          "secondary_size": [
            0.178,
            0.0525
          ],
          "secondary_offset": [
            0,
            0,
            0
          ],
          "position": [
            0.002,
            0,
            -0.0212
          ],
          "rotation": [
            0,
            0,
            0
          ]
        },
        "source": {
          "legacy_template": "Cylindrical_Base",
          "source_concept_index": 0
        }
      },
      {
        "template": "Curved_Spout",
        "semantic": "spout",
        "parameters": {
          "tube_radius": 0.0685,
          "end_extension_scale": 0.06,
          "bottom_start": [
            0,
            0,
            -0.068
          ],
          "bottom_offset": [
            0,
            0.5,
            0
          ],
          "arc_center_offset": [
            0,
            -0.05,
            0.36
          ],
          "spout_rotation_degrees": 160,
          "position": [
            0.002,
            0,
            -0.0212
          ],
          "rotation": [
            0,
            0,
            0
          ]
        },
        "source": {
          "legacy_template": "Curved_Spout",
          "source_concept_index": 1
        }
      },
      {
        "template": "RotaryY_Switch",
        "semantic": "switch",
        "parameters": {
          "main_size_1": [
            0.165,
            0.045
          ],
          "main_size_2": [
            0.057,
            0.535
          ],
          "switch_offsets_x": [
            -0.609,
            0.609
          ],
          "sub_size": [
            0.1,
            0.1,
            0.3798
          ],
          "sub_offset": 0,
          "tilt_degrees": 0,
          "first_rotation_degrees": -90,
          "second_rotation_degrees": 90,
          "switch_count": 2,
          "sub_count": 1,
          "position": [
            0.002,
            -0.5005000000000001,
            -0.0892
          ],
          "rotation": [
            0,
            0,
            0
          ]
        },
        "source": {
          "legacy_template": "RotaryY_Switch",
          "source_concept_index": 2
        }
      }
    ]
  }
}