{
  "format": "rewritten_category_object_parameters.v1",
  "category": "Faucet",
  "object": {
    "id": "c9c3fce5cf0e964f116162acefe23592",
    "type": "mesh",
    "source_object_index": 58,
    "concepts": [
      {
        "template": "Cylindrical_Base",
        "semantic": "base",
        "parameters": {
          "cylinder_count": 1,
          "primary_size": [
            0.125,
            0.645
          ],
          "secondary_size": [
            0.15,
            0.08
          ],
          "secondary_offset": [
            0,
            0,
            0
          ],
          "position": [
            0.052,
            -0.174,
            -0.042
          ],
          "rotation": [
            0,
            0,
            0
          ]
        },
        "source": {
          "legacy_template": "Cylindrical_Base",
          "source_concept_index": 0
        }
      },
      {
        "template": "Curved_Spout",
        "semantic": "spout",
        "parameters": {
          "tube_radius": 0.062,
          "end_extension_scale": 0.055,
          "bottom_start": [
            0,
            -0.02,
            -0.125
          ],
          "bottom_offset": [
            0,
            0.595,
            0
          ],
          "arc_center_offset": [
            0,
            -0.015,
            0.461
          ],
          "spout_rotation_degrees": 180,
          "position": [
            0.052,
            -0.174,
            -0.042
          ],
          "rotation": [
            0,
            0,
            0
          ]
        },
        "source": {
          "legacy_template": "Curved_Spout",
          "source_concept_index": 1
        }
      },
      {
        "template": "RegularX_Switch",
        "semantic": "switch",
        "parameters": {
          "main_size": [
            0.116,
            0.36
          ],
          "sub_size": [
            0.04,
            0.42
          ],
          "sub_offset": [
            -0.135,
            0
          ],
          "main_z_rotation_degrees": 0,
          "main_x_rotation_degrees": 0,
          "sub_rotation_degrees": 0,
          "position": [
            -0.323,
            -0.414,
            -0.169
          ],
          "rotation": [
            0,
            0,
            0
          ]
        },
        "source": {
          "legacy_template": "RegularX_Switch",
          "source_concept_index": 2
        }
      }
    ]
  }
}