{
  "format": "rewritten_category_object_parameters.v1",
  "category": "Display",
  "object": {
    "id": "2c5b951b726b7672c137fd38f49b032c",
    "type": "mesh",
    "source_object_index": 110,
    "concepts": [
      {
        "template": "FlatDisplayScreen",
        "semantic": "screen",
        "parameters": {
          "screen_size": [
            1.68,
            1.002,
            0.088
          ],
          "has_back_layer": true,
          "back_layer_size": [
            1.56,
            0.86,
            0.08
          ],
          "back_layer_offset": [
            0,
            0.01
          ],
          "position": [
            0,
            0.08,
            0.04
          ],
          "rotation": [
            0,
            0,
            0
          ]
        },
        "source": {
          "legacy_template": "Standard_Screen",
          "source_concept_index": 0
        }
      },
      {
        "template": "RectangularDisplaySupportSet",
        "semantic": "support",
        "parameters": {
          "support_count": 1,
          "support_size": [
            0.4,
            0.175,
            0.04
          ],
          "support_spacing": 0.1,
          "position": [
            -0.01,
            -0.34099999999999997,
            -0.060000000000000005
          ],
          "rotation": [
            0,
            0,
            0
          ]
        },
        "source": {
          "legacy_template": "Cuboidal_Support",
          "source_concept_index": 1
        }
      },
      {
        "template": "RectangularDisplayBase",
        "semantic": "base",
        "parameters": {
          "base_size": [
            0.87,
            0.04,
            0.39
          ],
          "base_rotation_degrees": 0,
          "position": [
            -0.01,
            -0.516,
            -0.04
          ],
          "rotation": [
            0,
            0,
            0
          ]
        },
        "source": {
          "legacy_template": "Cuboidal_Base",
          "source_concept_index": 2
        }
      }
    ]
  }
}