{
  "format": "rewritten_category_object_parameters.v1",
  "category": "Display",
  "object": {
    "id": "2c1e2873955b563920685b5a7e34b501",
    "type": "mesh",
    "source_object_index": 109,
    "concepts": [
      {
        "template": "FrustumDisplayScreen",
        "semantic": "screen",
        "parameters": {
          "has_front_layer": false,
          "front_layer_size": [
            1.56,
            1.225,
            0.07
          ],
          "back_shell_size": [
            1.155,
            1.01,
            0.0665
          ],
          "back_shell_offset": [
            0,
            0
          ],
          "position": [
            0,
            0.09,
            0.032
          ],
          "rotation": [
            0,
            0,
            0
          ]
        },
        "source": {
          "legacy_template": "Frustum_Screen",
          "source_concept_index": 0
        }
      },
      {
        "template": "TShapedDisplaySupport",
        "semantic": "support",
        "parameters": {
          "upper_bar_size": [
            0.31,
            0.305,
            0.03
          ],
          "upper_mount_point": [
            0,
            -0.4,
            0
          ],
          "middle_stem_size": [
            0.08,
            0.08,
            0.04
          ],
          "middle_front_offset": 0.01,
          "position": [
            0,
            0.09,
            -0.0345
          ],
          "rotation": [
            0,
            0,
            0
          ]
        },
        "source": {
          "legacy_template": "TShaped_Support",
          "source_concept_index": 1
        }
      },
      {
        "template": "CircularDisplayBase",
        "semantic": "base",
        "parameters": {
          "base_size": [
            0.16,
            0.305
          ],
          "base_rotation_degrees": 0,
          "position": [
            0.025,
            -0.5375000000000001,
            -0.0030000000000000027
          ],
          "rotation": [
            0,
            0,
            0
          ]
        },
        "source": {
          "legacy_template": "Round_Base",
          "source_concept_index": 2
        }
      }
    ]
  }
}