{
  "format": "rewritten_category_object_parameters.v1",
  "category": "Table",
  "object": {
    "id": "10139657dfa9afe0c3bd24f986301745",
    "type": "mesh",
    "source_object_index": 102,
    "concepts": [
      {
        "template": "CylindricalTableTop",
        "semantic": null,
        "parameters": {
          "size": [
            0.97,
            0.09
          ],
          "position": [
            0,
            0.25,
            0
          ],
          "rotation": [
            0,
            0,
            0
          ]
        },
        "source": {
          "legacy_template": "Cylindrical_desktop",
          "source_concept_index": 0
        }
      },
      {
        "template": "BarCylindricalTableLeg",
        "semantic": null,
        "parameters": {
          "support_size": [
            0.74,
            0.56
          ],
          "foot_size": [
            0.69,
            0.11
          ],
          "horizontal_pitch_degrees": 0,
          "extra_legs": [],
          "position": [
            0,
            0.20500000000000002,
            0
          ],
          "rotation": [
            0,
            0,
            0
          ]
        },
        "source": {
          "legacy_template": "Bar_cylindrical_leg",
          "source_concept_index": 1
        }
      }
    ]
  }
}